[
    null,
    {
        "id": 1,
        "animationId": 0,
        "consumable": false,
        "damage": {
            "critical": false,
            "elementId": 0,
            "formula": "0",
            "type": 0,
            "variance": 20
        },
        "description": "Resources necessary for survival",
        "effects": [],
        "hitType": 0,
        "iconIndex": 84,
        "itypeId": 3,
        "name": "Magic Power",
        "note": "<Menu Category: KeyItems>",
        "occasion": 3,
        "price": 0,
        "repeats": 1,
        "scope": 2,
        "speed": 0,
        "successRate": 100,
        "tpGain": 0
    },
    {
        "id": 2,
        "animationId": 41,
        "consumable": false,
        "damage": {
            "critical": false,
            "elementId": 0,
            "formula": "0",
            "type": 0,
            "variance": 20
        },
        "description": "Measure of experience",
        "effects": [],
        "hitType": 0,
        "iconIndex": 4,
        "itypeId": 3,
        "name": "Experience Index",
        "note": "",
        "occasion": 3,
        "price": 0,
        "repeats": 1,
        "scope": 0,
        "speed": 0,
        "successRate": 100,
        "tpGain": 0
    },
    {
        "id": 3,
        "animationId": 45,
        "consumable": true,
        "damage": {
            "critical": false,
            "elementId": 0,
            "formula": "0",
            "type": 0,
            "variance": 20
        },
        "description": "",
        "effects": [
            {
                "code": 22,
                "dataId": 4,
                "value1": 1,
                "value2": 0
            },
            {
                "code": 22,
                "dataId": 5,
                "value1": 1,
                "value2": 0
            },
            {
                "code": 22,
                "dataId": 6,
                "value1": 1,
                "value2": 0
            },
            {
                "code": 22,
                "dataId": 7,
                "value1": 1,
                "value2": 0
            },
            {
                "code": 22,
                "dataId": 8,
                "value1": 1,
                "value2": 0
            },
            {
                "code": 22,
                "dataId": 9,
                "value1": 1,
                "value2": 0
            },
            {
                "code": 22,
                "dataId": 10,
                "value1": 1,
                "value2": 0
            }
        ],
        "hitType": 0,
        "iconIndex": 176,
        "itypeId": 1,
        "name": "Herb for Dispelling Magic",
        "note": "",
        "occasion": 0,
        "price": 200,
        "repeats": 1,
        "scope": 7,
        "speed": 0,
        "successRate": 100,
        "tpGain": 0
    },
    {
        "id": 4,
        "animationId": 49,
        "consumable": true,
        "damage": {
            "critical": false,
            "elementId": 0,
            "formula": "b.mhp / 2",
            "type": 3,
            "variance": 20
        },
        "description": "",
        "effects": [
            {
                "code": 22,
                "dataId": 1,
                "value1": 1,
                "value2": 0
            }
        ],
        "hitType": 0,
        "iconIndex": 176,
        "itypeId": 1,
        "name": "Stimulant",
        "note": "",
        "occasion": 0,
        "price": 300,
        "repeats": 1,
        "scope": 9,
        "speed": 0,
        "successRate": 100,
        "tpGain": 0
    },
    {
        "id": 5,
        "animationId": 0,
        "consumable": false,
        "damage": {
            "critical": false,
            "elementId": 0,
            "formula": "0",
            "type": 0,
            "variance": 20
        },
        "description": "",
        "effects": [],
        "hitType": 0,
        "iconIndex": 0,
        "itypeId": 3,
        "name": "\\fs[14]textupeki@SExCOM.com <br> \\fs[18] \\V[281]",
        "note": "<SGCategory:警備会社>\n<SGDescription:\n\n\n\\fs[14] 差出人：textupeki@SExCOM.com\n 件名：派遣社員の評価資料をお送りいたします。\n\n\\fs[22]  いつもお世話になっております。SExCOMでございます。\n\n ご紹介いただいた咲姫様に対する弊社での評価は、非常に良好でした。\n\n 咲姫様がいらしてくだされば、残業も辞さないという意見も多々ありました。\n\n 業務実績はもちろん、社員の満足度も上昇したため、とても感謝しております。\n\n 今回のような人選を、今後もぜひともお願いできればと思っております。\n\n それでは、今後ともよろしくお願いいたします。\n>\n",
        "occasion": 0,
        "price": 0,
        "repeats": 1,
        "scope": 7,
        "speed": 0,
        "successRate": 100,
        "tpGain": 0
    },
    {
        "id": 6,
        "animationId": 0,
        "consumable": false,
        "damage": {
            "critical": false,
            "elementId": 0,
            "formula": "0",
            "type": 0,
            "variance": 20
        },
        "description": "",
        "effects": [],
        "hitType": 0,
        "iconIndex": 0,
        "itypeId": 3,
        "name": "\\fs[14]textupeki@SExCOM.com <br> \\fs[18] \\V[282]",
        "note": "<SGCategory:警備会社>\n<SGDescription:\n\n\n\\fs[14] 差出人：textupeki@SExCOM.com\n 件名：派遣社員の評価資料をお送りいたします。\n\n\\fs[22]  いつもお世話になっております。SExCOMでございます。\n\n 最近派遣業務を担当しております咲姫様への評価が非常に高いと見られます。\n\n 福利厚生のためのペット程度の認識でしたが、\n\n 今後の実務処理において評価を再考するべきだという意見がありました。\n\n 素晴らしき人選、心より感謝申しあげます。\n\n 今後ともよろしくお願いいたします。\n>\n",
        "occasion": 0,
        "price": 0,
        "repeats": 1,
        "scope": 7,
        "speed": 0,
        "successRate": 100,
        "tpGain": 0
    },
    {
        "id": 7,
        "animationId": 0,
        "consumable": false,
        "damage": {
            "critical": false,
            "elementId": 0,
            "formula": "0",
            "type": 0,
            "variance": 20
        },
        "description": "",
        "effects": [],
        "hitType": 0,
        "iconIndex": 0,
        "itypeId": 3,
        "name": "\\fs[14]textupeki@SExCOM.com <br> \\fs[18] \\V[283]",
        "note": "<SGCategory:警備会社>\n<SGDescription:\n\n\n\\fs[14] 差出人：textupeki@SExCOM.com\n 件名：派遣社員の評価資料をお送りいたします。\n\n\\fs[22]  いつもお世話になっております。SExCOMでございます。\n\n 派遣業務担当の咲姫ちゃんへの評価が日々向上しております。\n\n 何とお礼を申しあげてよいか、お礼の言葉もございません。福利厚生はやはり淫魔第一産業からの派遣ですね。\n\n 雰囲気に流されやすいチョロさや、どんなプレイでも引きうけてくれる丈夫さが魅力ポイントと言いましょうか。\n\n 肉便器アイドルという名誉あるあだ名まで付いたほどです。\n\n それでは、今後ともよろしくお願いいたします。\n>\n",
        "occasion": 0,
        "price": 0,
        "repeats": 1,
        "scope": 7,
        "speed": 0,
        "successRate": 100,
        "tpGain": 0
    },
    {
        "id": 8,
        "animationId": 0,
        "consumable": false,
        "damage": {
            "critical": false,
            "elementId": 0,
            "formula": "0",
            "type": 0,
            "variance": 20
        },
        "description": "",
        "effects": [],
        "hitType": 0,
        "iconIndex": 0,
        "itypeId": 3,
        "name": "\\fs[14]textupeki@SExCOM.com <br> \\fs[18] \\V[284]",
        "note": "<SGCategory:警備会社>\n<SGDescription:\n\n\n\\fs[14] 差出人：textupeki@SExCOM.com\n 件名：派遣社員の評価資料をお送りいたします。\n\n\\fs[22]  いつもお世話になっております。SExCOMでございます。\n\n 咲姫様の派遣業務において些細なトラブルがあったと存じております。\n\n ほかのチームや他社からの派遣に比べて非常に評価が高いため、\n\n なにとぞ円満な協力関係を維持していきたい所存でございます。\n\n メアリー様には常々お力添えいただいてばかりですので、\n\n ご不明な点などがございましたら、いつでもご連絡ください。\n\n>\n",
        "occasion": 0,
        "price": 0,
        "repeats": 1,
        "scope": 7,
        "speed": 0,
        "successRate": 100,
        "tpGain": 0
    },
    {
        "id": 9,
        "animationId": 0,
        "consumable": true,
        "damage": {
            "critical": false,
            "elementId": 0,
            "formula": "0",
            "type": 0,
            "variance": 20
        },
        "description": "",
        "effects": [],
        "hitType": 0,
        "iconIndex": 0,
        "itypeId": 1,
        "name": "",
        "note": "",
        "occasion": 0,
        "price": 0,
        "repeats": 1,
        "scope": 7,
        "speed": 0,
        "successRate": 100,
        "tpGain": 0
    },
    {
        "id": 10,
        "animationId": 0,
        "consumable": true,
        "damage": {
            "critical": false,
            "elementId": 0,
            "formula": "0",
            "type": 0,
            "variance": 20
        },
        "description": "",
        "effects": [],
        "hitType": 0,
        "iconIndex": 0,
        "itypeId": 3,
        "name": "\\fs[14]yari_man@dokage_maga.com <br> \\fs[18] \\V[286]",
        "note": "<SGCategory:マスコミ>\n<SGDescription:\n\n\n\\fs[14] 差出人：yari_man@dokage_maga.com\n タイトル：【トカゲマガジン】新入社員の撮影企画への派遣依頼\n\n\\fs[22]  お世話になっております。先日は素晴らしい人材を派遣していただき、ありがとうございました。\n\n おかげで良い結果を出すことができました。\n\n 現場での反応も良かったため、末長く一緒にお仕事ができればと思っております。\n\n とくに、あの神経質な取材者が気に入っておりました。\n\n 次の企画においても同じ人材を編成することを前提としておりますので、添付した企画書のご確認をお願いいたします。\n\n 今後ともよろしくお願いいたします。\n>",
        "occasion": 0,
        "price": 0,
        "repeats": 1,
        "scope": 7,
        "speed": 0,
        "successRate": 100,
        "tpGain": 0
    },
    {
        "id": 11,
        "animationId": 0,
        "consumable": true,
        "damage": {
            "critical": false,
            "elementId": 0,
            "formula": "0",
            "type": 0,
            "variance": 20
        },
        "description": "",
        "effects": [],
        "hitType": 0,
        "iconIndex": 0,
        "itypeId": 3,
        "name": "\\fs[14]yari_man@dokage_maga.com <br> \\fs[18] \\V[287]",
        "note": "<SGCategory:マスコミ>\n<SGDescription:\n\n\n\\fs[14] 差出人：yari_man@dokage_maga.com\n タイトル：【トカゲマガジン】ネット配信企画への人材派遣依頼\n\n\\fs[22]  お世話になっております。先日派遣していただいた人材の件でご連絡いたしました。\n\n 弊社内部でも懐疑的な意見が多かったのですが、メアリー様推進力のおかげで無事企画が通ったこと、あらためて感謝の言葉を申しあげます。\n\n 撮影分が放送されなった件につきましては、別途添付いたしました文書をご確認ください。\n\n 本来なら貴社側に責任がございますが、今後とも良い関係を築いていきたいという弊社の要望に従って、このように処理させていただきました。\n\n 今後ともよろしくお願いいたします。\n>",
        "occasion": 0,
        "price": 0,
        "repeats": 1,
        "scope": 7,
        "speed": 0,
        "successRate": 100,
        "tpGain": 0
    },
    {
        "id": 12,
        "animationId": 0,
        "consumable": true,
        "damage": {
            "critical": false,
            "elementId": 0,
            "formula": "0",
            "type": 0,
            "variance": 20
        },
        "description": "",
        "effects": [],
        "hitType": 0,
        "iconIndex": 0,
        "itypeId": 3,
        "name": "\\fs[14]yari_man@dokage_maga.com <br> \\fs[18] \\V[288]",
        "note": "<SGCategory:マスコミ>\n<SGDescription:\n\n\n\\fs[14] 差出人：yari_man@dokage_maga.com\n タイトル：【トカゲマガジン】派遣社員の指定依頼\n\n\\fs[22]  お世話になっております。トカゲマガジンの人事担当でございます。\n\n このたびの撮影の打ち上げの際に発生した咲姫様の件について、連絡事項がございますのでお知らせいたします。\n\n 弊社の調べによりますと、咲姫様が倒れたのはただの過剰飲酒によるもので、雰囲気はいつもの打ち上げと変わらなかったかったとのことです。\n\n もちろん派遣社員を管理できなかった弊社の責任もございますので、あらためて謝罪の言葉を申しあげます。\n\n この件が貴社との協力関係に支障をきたしませんよう、なにとぞご理解のほどよろしくお願いいたします。\n>\n",
        "occasion": 0,
        "price": 0,
        "repeats": 1,
        "scope": 7,
        "speed": 0,
        "successRate": 100,
        "tpGain": 0
    },
    {
        "id": 13,
        "animationId": 0,
        "consumable": true,
        "damage": {
            "critical": false,
            "elementId": 0,
            "formula": "0",
            "type": 0,
            "variance": 20
        },
        "description": "",
        "effects": [],
        "hitType": 0,
        "iconIndex": 0,
        "itypeId": 3,
        "name": "\\fs[14]yari_man@dokage_maga.com <br> \\fs[18] \\V[289]",
        "note": "<SGCategory:マスコミ>\n<SGDescription:\n\n\n\\fs[14] 差出人：yari_man@dokage_maga.com\n タイトル：【トカゲマガジン】新規プラットフォームの宣伝のための人材派遣依頼\n\n\\fs[22]  お世話になっております。トカゲマガジンの人事担当でございます。\n\n まず、いくつかの衝突があったにもかかわらず、弊社の要望に応えてくださったこと、心より感謝申しあげます。\n\n 新規プラットフォームのスタートとして非常にふさわしい人材であったと弊社では判断しており、これに従い、お約束通り収益の一部を貴社と配分することになりました。\n\n 内容に関しましては、添付したファイルをご確認いただけますと幸いです。\n\n 今後ともよろしくお願いいたします。\n\n 重ねてお礼申しあげます。\n\n>\n",
        "occasion": 0,
        "price": 0,
        "repeats": 1,
        "scope": 7,
        "speed": 0,
        "successRate": 100,
        "tpGain": 0
    },
    {
        "id": 14,
        "animationId": 0,
        "consumable": true,
        "damage": {
            "critical": false,
            "elementId": 0,
            "formula": "0",
            "type": 0,
            "variance": 20
        },
        "description": "",
        "effects": [],
        "hitType": 0,
        "iconIndex": 0,
        "itypeId": 1,
        "name": "",
        "note": "",
        "occasion": 0,
        "price": 0,
        "repeats": 1,
        "scope": 7,
        "speed": 0,
        "successRate": 100,
        "tpGain": 0
    },
    {
        "id": 15,
        "animationId": 0,
        "consumable": true,
        "damage": {
            "critical": false,
            "elementId": 0,
            "formula": "0",
            "type": 0,
            "variance": 20
        },
        "description": "",
        "effects": [],
        "hitType": 0,
        "iconIndex": 0,
        "itypeId": 3,
        "name": "\\fs[14]project_pregnancy@inmalabo.com <br> \\fs[18] \\V[291]",
        "note": "<SGCategory:研究機関>\n<SGDescription:\n\n\n\\fs[14] 差出人：project_pregnancy@inmalabo.com\n タイトル：【InmaLabo】新規プロジェクトの臨床実験募集について\n\n\\fs[22]  お世話になっております。研究リームのリーダーです。このたび、新規プロジェクトを担当することになりました。\n\n 実験途中、反抗をするという問題がございましたが、先日紹介していただいたとおり\n\n 丈夫で感度も良く、優れた臨床対象であったというのが研究機関の意見です。\n\n 次の臨床実験のご案内と募集要件を別途送付いたしますので、ご確認ならびにご対応のほどよろしくお願いいたします。\n\n 今回の実験結果と連携する項目が多数存在するため、\n\n なるべく同じ対象で実験を進めたいと思っております。\n\n>\n",
        "occasion": 0,
        "price": 0,
        "repeats": 1,
        "scope": 7,
        "speed": 0,
        "successRate": 100,
        "tpGain": 0
    },
    {
        "id": 16,
        "animationId": 0,
        "consumable": true,
        "damage": {
            "critical": false,
            "elementId": 0,
            "formula": "0",
            "type": 0,
            "variance": 20
        },
        "description": "",
        "effects": [],
        "hitType": 0,
        "iconIndex": 0,
        "itypeId": 3,
        "name": "\\fs[14]project_pregnancy@inmalabo.com <br> \\fs[18] \\V[292]",
        "note": "<SGCategory:研究機関>\n<SGDescription:\n\n\n\\fs[14] 差出人：project_pregnancy@inmalabo.com\n タイトル：【InmaLabo】臨床実験に関する内容と次回の実験対象の依頼について\n\n\n\\fs[22]  今回の実験と今後の実験に関する資料を送付いたします。\n\n 次のスケジュールのご案内および派遣社員の勤怠資料をお送りいたします。\n\n 耐久性と感度においては依然として素晴らしい指標を見せているため、\n\n 引き続き素晴らしい臨床対象をお願いする所存でございますが、\n\n 精密な実験結果を収集する場所のため、実験後の衛生管理につきましては十分ご注意いただきますようお願いいたします。\n\n より多くの実験結果が必要になりましたため、\n\n 今回の実験対象に加え、様々な候補群をご紹介いただきたく存じます。\n\n 関連事項は別途送付いたしますので、ご確認のうえ、早急にご対応いただけますと幸いです。\n\n>\n",
        "occasion": 0,
        "price": 0,
        "repeats": 1,
        "scope": 7,
        "speed": 0,
        "successRate": 100,
        "tpGain": 0
    },
    {
        "id": 17,
        "animationId": 0,
        "consumable": true,
        "damage": {
            "critical": false,
            "elementId": 0,
            "formula": "0",
            "type": 0,
            "variance": 20
        },
        "description": "",
        "effects": [],
        "hitType": 0,
        "iconIndex": 0,
        "itypeId": 3,
        "name": "\\fs[14]project_pregnancy@inmalabo.com <br> \\fs[18] \\V[293]",
        "note": "<SGCategory:研究機関>\n<SGDescription:\n\n\n\\fs[14] 差出人：project_pregnancy@inmalabo.com\n タイトル：【InmaLabo】派遣に関する資料および注意事項の送付について\n\n\\fs[22]  次のスケジュールのご案内および関連注意事項を送付いたします。\n\n 実験は順調ですが、臨床対象に本施設を拒む傾向が見られるため\n\n 円滑な実験対象の供給をお願いいたします。\n\n なお、このような実務者への攻撃的な態度は\n\n 貴社の評価反映に不利益をもたらす恐れがありますので、ご注意ください。\n\n 次の実験に関する事項を添付したしますので、ご確認をお願いいたします。\n\n\n>\n",
        "occasion": 0,
        "price": 0,
        "repeats": 1,
        "scope": 7,
        "speed": 0,
        "successRate": 100,
        "tpGain": 0
    },
    {
        "id": 18,
        "animationId": 0,
        "consumable": true,
        "damage": {
            "critical": false,
            "elementId": 0,
            "formula": "0",
            "type": 0,
            "variance": 20
        },
        "description": "",
        "effects": [],
        "hitType": 0,
        "iconIndex": 0,
        "itypeId": 3,
        "name": "\\fs[14]project_pregnancy@inmalabo.com <br> \\fs[18] \\V[294]",
        "note": "<SGCategory:研究機関>\n<SGDescription:\n\n\n\\fs[14] 差出人：project_pregnancy@inmalabo.com\n タイトル：【InmaLabo】今後の実験に関する内容送付について\n\n\\fs[22]  実験終了および今後の予定についてご案内いたします。\n\n ご協力により、このたびの実験は終了いたしました。\n\n 今後の臨床実験に関してましては、スケジュールが決まり次第ご連絡いたします。\n\n ご協力いただきありがとうございました。今後とも、どうぞよろしくお願い申しあげます。\n\n\n>\n",
        "occasion": 0,
        "price": 0,
        "repeats": 1,
        "scope": 7,
        "speed": 0,
        "successRate": 100,
        "tpGain": 0
    },
    {
        "id": 19,
        "animationId": 0,
        "consumable": true,
        "damage": {
            "critical": false,
            "elementId": 0,
            "formula": "0",
            "type": 0,
            "variance": 20
        },
        "description": "",
        "effects": [],
        "hitType": 0,
        "iconIndex": 0,
        "itypeId": 1,
        "name": "",
        "note": "",
        "occasion": 0,
        "price": 0,
        "repeats": 1,
        "scope": 7,
        "speed": 0,
        "successRate": 100,
        "tpGain": 0
    },
    {
        "id": 20,
        "animationId": 0,
        "consumable": true,
        "damage": {
            "critical": false,
            "elementId": 0,
            "formula": "0",
            "type": 0,
            "variance": 20
        },
        "description": "",
        "effects": [],
        "hitType": 0,
        "iconIndex": 0,
        "itypeId": 3,
        "name": "\\fs[14]saimin@circulation.com <br> \\fs[18] \\V[296]",
        "note": "<SGCategory:物流会社>\n<SGDescription:\n\n\n\\fs[14] 差出人：saimin@circulation.com\n タイトル：営業アシスタント社員に関する業務評価の送付\n\n\\fs[22]  お世話になっております。ご依頼いただいた派遣社員についての詳細を送付いたします。\n\n 業務に対する熟練度が低い新入社員ではありますが、\n\n 社交性や心構えなど、将来性が期待できるため高く評価しております。\n\n 実務能力を磨けば完璧でしょう。\n\n 未熟な部分はございますが、仕事に誠実に取りくんでおり\n\n 将来も期待できるため、今後も当社員の派遣をお願いしたく存じます。\n\n なにとぞよろしくお願いいたします。\n>\n",
        "occasion": 0,
        "price": 0,
        "repeats": 1,
        "scope": 7,
        "speed": 0,
        "successRate": 100,
        "tpGain": 0
    },
    {
        "id": 21,
        "animationId": 0,
        "consumable": true,
        "damage": {
            "critical": false,
            "elementId": 0,
            "formula": "0",
            "type": 0,
            "variance": 20
        },
        "description": "",
        "effects": [],
        "hitType": 0,
        "iconIndex": 0,
        "itypeId": 3,
        "name": "\\fs[14]saimin@circulation.com <br> \\fs[18] \\V[297]",
        "note": "<SGCategory:物流会社>\n<SGDescription:\n\n\n\\fs[14] 差出人：saimin@circulation.com\n タイトル：派遣社員の業務評価および宣伝効果\n\n\\fs[22]  いつもお世話になっております。 \n\n 最近、派遣を担当されている咲姫社員に対する友好的な評価が多く見られます。\n\n 弊社と高い信頼関係を築いており、\n\n ぶしつけなお願いにもいつも笑顔で対応してくださるところが主な評価ポイントです。\n\n その点に関しましては、心よりお詫び申しあげます。\n\n 誠実かつ積極的な態度で仕事に臨んでくださり、大変助かっております。\n\n 今後もぜひ、この協力関係を保っていきたいと考えております。\n\n 引き続きよろしくお願いいたします。\n>\n",
        "occasion": 0,
        "price": 0,
        "repeats": 1,
        "scope": 7,
        "speed": 0,
        "successRate": 100,
        "tpGain": 0
    },
    {
        "id": 22,
        "animationId": 0,
        "consumable": true,
        "damage": {
            "critical": false,
            "elementId": 0,
            "formula": "0",
            "type": 0,
            "variance": 20
        },
        "description": "",
        "effects": [],
        "hitType": 0,
        "iconIndex": 0,
        "itypeId": 3,
        "name": "\\fs[14]saimin@circulation.com <br> \\fs[18] \\V[298]",
        "note": "<SGCategory:物流会社>\n<SGDescription:\n\n\n\\fs[14] 差出人：saimin@circulation.com\n タイトル：宣伝社員の派遣に関する内容送付\n\n\\fs[22]  いつもお世話になっております。 \n\n 単刀直入に申しますが、社内の盗撮はいくら協力社でも困ります。\n\n お手軽オナホの分際で業務の進行に損害をきたすと大問題になりますので、気を付けてください。\n\n 空気が読めるのは高く評価しますが、接客のときだけでお願いします。\n\n 相互間の損益に関する理解は依然として一致していると考えられますので、\n\n 今までどおり、便利なオナホを提供していただければと存じます。よろしくお願いいたします。\n\n>\n",
        "occasion": 0,
        "price": 0,
        "repeats": 1,
        "scope": 7,
        "speed": 0,
        "successRate": 100,
        "tpGain": 0
    },
    {
        "id": 23,
        "animationId": 0,
        "consumable": true,
        "damage": {
            "critical": false,
            "elementId": 0,
            "formula": "0",
            "type": 0,
            "variance": 20
        },
        "description": "",
        "effects": [],
        "hitType": 0,
        "iconIndex": 0,
        "itypeId": 3,
        "name": "\\fs[14]saimin@circulation.com <br> \\fs[18] \\V[299]",
        "note": "<SGCategory:物流会社>\n<SGDescription:\n\n\n\\fs[14] 差出人：saimin@circulation.com\n タイトル：今後の宣伝社員の派遣スケジュールについて\n\n\\fs[22]  いつもお世話になっております。 \n\n 急な依頼にもかかわらず多数の人材を迅速に手配してくださり、大変助かりました。\n\n さすがメアリー様のチーム員といいましょうか。容姿とテクニックはもちろんのうえ、\n\n 催眠にかかりやすかったため、使い勝手が大変良かったです。\n\n ただ、チーム全体の派遣を依頼したのにメアリー様がいらっしゃらなかったのは残念です。\n\n チームメンバーだけでなく、名高いメアリー様ともお会いできる機会がほしいですね。\n\n 色々な言い訳を作って避けておられますが、近いうちにお会いすることになるでしょう。\n\n 引き続きよろしくお願いいたします。\n>\n",
        "occasion": 0,
        "price": 0,
        "repeats": 1,
        "scope": 7,
        "speed": 0,
        "successRate": 100,
        "tpGain": 0
    },
    {
        "id": 24,
        "animationId": 0,
        "consumable": true,
        "damage": {
            "critical": false,
            "elementId": 0,
            "formula": "0",
            "type": 0,
            "variance": 20
        },
        "description": "",
        "effects": [],
        "hitType": 0,
        "iconIndex": 0,
        "itypeId": 1,
        "name": "",
        "note": "",
        "occasion": 0,
        "price": 0,
        "repeats": 1,
        "scope": 7,
        "speed": 0,
        "successRate": 100,
        "tpGain": 0
    },
    {
        "id": 25,
        "animationId": 0,
        "consumable": true,
        "damage": {
            "critical": false,
            "elementId": 0,
            "formula": "0",
            "type": 0,
            "variance": 20
        },
        "description": "",
        "effects": [],
        "hitType": 0,
        "iconIndex": 0,
        "itypeId": 1,
        "name": "",
        "note": "",
        "occasion": 0,
        "price": 0,
        "repeats": 1,
        "scope": 7,
        "speed": 0,
        "successRate": 100,
        "tpGain": 0
    },
    {
        "id": 26,
        "animationId": 0,
        "consumable": true,
        "damage": {
            "critical": false,
            "elementId": 0,
            "formula": "0",
            "type": 0,
            "variance": 20
        },
        "description": "",
        "effects": [],
        "hitType": 0,
        "iconIndex": 0,
        "itypeId": 1,
        "name": "",
        "note": "",
        "occasion": 0,
        "price": 0,
        "repeats": 1,
        "scope": 7,
        "speed": 0,
        "successRate": 100,
        "tpGain": 0
    },
    {
        "id": 27,
        "animationId": 0,
        "consumable": true,
        "damage": {
            "critical": false,
            "elementId": 0,
            "formula": "0",
            "type": 0,
            "variance": 20
        },
        "description": "",
        "effects": [],
        "hitType": 0,
        "iconIndex": 0,
        "itypeId": 1,
        "name": "",
        "note": "",
        "occasion": 0,
        "price": 0,
        "repeats": 1,
        "scope": 7,
        "speed": 0,
        "successRate": 100,
        "tpGain": 0
    },
    {
        "id": 28,
        "animationId": 0,
        "consumable": true,
        "damage": {
            "critical": false,
            "elementId": 0,
            "formula": "0",
            "type": 0,
            "variance": 20
        },
        "description": "",
        "effects": [],
        "hitType": 0,
        "iconIndex": 0,
        "itypeId": 1,
        "name": "",
        "note": "",
        "occasion": 0,
        "price": 0,
        "repeats": 1,
        "scope": 7,
        "speed": 0,
        "successRate": 100,
        "tpGain": 0
    },
    {
        "id": 29,
        "animationId": 0,
        "consumable": true,
        "damage": {
            "critical": false,
            "elementId": 0,
            "formula": "0",
            "type": 0,
            "variance": 20
        },
        "description": "",
        "effects": [],
        "hitType": 0,
        "iconIndex": 0,
        "itypeId": 1,
        "name": "",
        "note": "",
        "occasion": 0,
        "price": 0,
        "repeats": 1,
        "scope": 7,
        "speed": 0,
        "successRate": 100,
        "tpGain": 0
    },
    {
        "id": 30,
        "animationId": 0,
        "consumable": true,
        "damage": {
            "critical": false,
            "elementId": 0,
            "formula": "0",
            "type": 0,
            "variance": 20
        },
        "description": "",
        "effects": [],
        "hitType": 0,
        "iconIndex": 0,
        "itypeId": 1,
        "name": "",
        "note": "",
        "occasion": 0,
        "price": 0,
        "repeats": 1,
        "scope": 7,
        "speed": 0,
        "successRate": 100,
        "tpGain": 0
    },
    {
        "id": 31,
        "animationId": 0,
        "consumable": true,
        "damage": {
            "critical": false,
            "elementId": 0,
            "formula": "0",
            "type": 0,
            "variance": 20
        },
        "description": "",
        "effects": [],
        "hitType": 0,
        "iconIndex": 0,
        "itypeId": 3,
        "name": "Number01",
        "note": "",
        "occasion": 3,
        "price": 0,
        "repeats": 1,
        "scope": 7,
        "speed": 0,
        "successRate": 100,
        "tpGain": 0
    },
    {
        "id": 32,
        "animationId": 0,
        "consumable": false,
        "damage": {
            "critical": false,
            "elementId": 0,
            "formula": "0",
            "type": 0,
            "variance": 20
        },
        "description": "",
        "effects": [],
        "hitType": 0,
        "iconIndex": 160,
        "itypeId": 3,
        "name": "Number02",
        "note": "",
        "occasion": 3,
        "price": 0,
        "repeats": 1,
        "scope": 7,
        "speed": 0,
        "successRate": 100,
        "tpGain": 0
    },
    {
        "id": 33,
        "animationId": 0,
        "consumable": true,
        "damage": {
            "critical": false,
            "elementId": 0,
            "formula": "0",
            "type": 0,
            "variance": 20
        },
        "description": "",
        "effects": [],
        "hitType": 0,
        "iconIndex": 0,
        "itypeId": 3,
        "name": "Number03",
        "note": "",
        "occasion": 0,
        "price": 0,
        "repeats": 1,
        "scope": 7,
        "speed": 0,
        "successRate": 100,
        "tpGain": 0
    },
    {
        "id": 34,
        "animationId": 0,
        "consumable": true,
        "damage": {
            "critical": false,
            "elementId": 0,
            "formula": "0",
            "type": 0,
            "variance": 20
        },
        "description": "",
        "effects": [],
        "hitType": 0,
        "iconIndex": 0,
        "itypeId": 3,
        "name": "Number04",
        "note": "",
        "occasion": 0,
        "price": 0,
        "repeats": 1,
        "scope": 7,
        "speed": 0,
        "successRate": 100,
        "tpGain": 0
    },
    {
        "id": 35,
        "animationId": 0,
        "consumable": true,
        "damage": {
            "critical": false,
            "elementId": 0,
            "formula": "0",
            "type": 0,
            "variance": 20
        },
        "description": "",
        "effects": [],
        "hitType": 0,
        "iconIndex": 0,
        "itypeId": 3,
        "name": "Number05",
        "note": "",
        "occasion": 0,
        "price": 0,
        "repeats": 1,
        "scope": 7,
        "speed": 0,
        "successRate": 100,
        "tpGain": 0
    },
    {
        "id": 36,
        "animationId": 0,
        "consumable": true,
        "damage": {
            "critical": false,
            "elementId": 0,
            "formula": "0",
            "type": 0,
            "variance": 20
        },
        "description": "",
        "effects": [],
        "hitType": 0,
        "iconIndex": 0,
        "itypeId": 3,
        "name": "Number06",
        "note": "",
        "occasion": 0,
        "price": 0,
        "repeats": 1,
        "scope": 7,
        "speed": 0,
        "successRate": 100,
        "tpGain": 0
    },
    {
        "id": 37,
        "animationId": 0,
        "consumable": true,
        "damage": {
            "critical": false,
            "elementId": 0,
            "formula": "0",
            "type": 0,
            "variance": 20
        },
        "description": "",
        "effects": [],
        "hitType": 0,
        "iconIndex": 0,
        "itypeId": 3,
        "name": "Number07",
        "note": "",
        "occasion": 0,
        "price": 0,
        "repeats": 1,
        "scope": 7,
        "speed": 0,
        "successRate": 100,
        "tpGain": 0
    },
    {
        "id": 38,
        "animationId": 0,
        "consumable": true,
        "damage": {
            "critical": false,
            "elementId": 0,
            "formula": "0",
            "type": 0,
            "variance": 20
        },
        "description": "",
        "effects": [],
        "hitType": 0,
        "iconIndex": 0,
        "itypeId": 3,
        "name": "Number08",
        "note": "",
        "occasion": 0,
        "price": 0,
        "repeats": 1,
        "scope": 7,
        "speed": 0,
        "successRate": 100,
        "tpGain": 0
    },
    {
        "id": 39,
        "animationId": 0,
        "consumable": true,
        "damage": {
            "critical": false,
            "elementId": 0,
            "formula": "0",
            "type": 0,
            "variance": 20
        },
        "description": "",
        "effects": [],
        "hitType": 0,
        "iconIndex": 0,
        "itypeId": 3,
        "name": "CNumber01",
        "note": "",
        "occasion": 0,
        "price": 0,
        "repeats": 1,
        "scope": 7,
        "speed": 0,
        "successRate": 100,
        "tpGain": 0
    },
    {
        "id": 40,
        "animationId": 0,
        "consumable": true,
        "damage": {
            "critical": false,
            "elementId": 0,
            "formula": "0",
            "type": 0,
            "variance": 20
        },
        "description": "",
        "effects": [],
        "hitType": 0,
        "iconIndex": 0,
        "itypeId": 3,
        "name": "CNumber02",
        "note": "",
        "occasion": 0,
        "price": 0,
        "repeats": 1,
        "scope": 7,
        "speed": 0,
        "successRate": 100,
        "tpGain": 0
    },
    {
        "id": 41,
        "animationId": 0,
        "consumable": true,
        "damage": {
            "critical": false,
            "elementId": 0,
            "formula": "0",
            "type": 0,
            "variance": 20
        },
        "description": "",
        "effects": [],
        "hitType": 0,
        "iconIndex": 0,
        "itypeId": 3,
        "name": "CNumber03",
        "note": "",
        "occasion": 3,
        "price": 0,
        "repeats": 1,
        "scope": 7,
        "speed": 0,
        "successRate": 100,
        "tpGain": 0
    },
    {
        "id": 42,
        "animationId": 0,
        "consumable": true,
        "damage": {
            "critical": false,
            "elementId": 0,
            "formula": "0",
            "type": 0,
            "variance": 20
        },
        "description": "",
        "effects": [],
        "hitType": 0,
        "iconIndex": 0,
        "itypeId": 3,
        "name": "CNumber04",
        "note": "",
        "occasion": 3,
        "price": 0,
        "repeats": 1,
        "scope": 7,
        "speed": 0,
        "successRate": 100,
        "tpGain": 0
    },
    {
        "id": 43,
        "animationId": 0,
        "consumable": true,
        "damage": {
            "critical": false,
            "elementId": 0,
            "formula": "0",
            "type": 0,
            "variance": 20
        },
        "description": "",
        "effects": [],
        "hitType": 0,
        "iconIndex": 0,
        "itypeId": 1,
        "name": "",
        "note": "",
        "occasion": 0,
        "price": 0,
        "repeats": 1,
        "scope": 7,
        "speed": 0,
        "successRate": 100,
        "tpGain": 0
    },
    {
        "id": 44,
        "animationId": 0,
        "consumable": true,
        "damage": {
            "critical": false,
            "elementId": 0,
            "formula": "0",
            "type": 0,
            "variance": 20
        },
        "description": "",
        "effects": [],
        "hitType": 0,
        "iconIndex": 0,
        "itypeId": 1,
        "name": "",
        "note": "",
        "occasion": 0,
        "price": 0,
        "repeats": 1,
        "scope": 7,
        "speed": 0,
        "successRate": 100,
        "tpGain": 0
    },
    {
        "id": 45,
        "animationId": 0,
        "consumable": true,
        "damage": {
            "critical": false,
            "elementId": 0,
            "formula": "0",
            "type": 0,
            "variance": 20
        },
        "description": "",
        "effects": [],
        "hitType": 0,
        "iconIndex": 0,
        "itypeId": 1,
        "name": "",
        "note": "",
        "occasion": 0,
        "price": 0,
        "repeats": 1,
        "scope": 7,
        "speed": 0,
        "successRate": 100,
        "tpGain": 0
    },
    {
        "id": 46,
        "animationId": 0,
        "consumable": true,
        "damage": {
            "critical": false,
            "elementId": 0,
            "formula": "0",
            "type": 0,
            "variance": 20
        },
        "description": "",
        "effects": [],
        "hitType": 0,
        "iconIndex": 0,
        "itypeId": 1,
        "name": "",
        "note": "",
        "occasion": 0,
        "price": 0,
        "repeats": 1,
        "scope": 7,
        "speed": 0,
        "successRate": 100,
        "tpGain": 0
    },
    {
        "id": 47,
        "animationId": 0,
        "consumable": true,
        "damage": {
            "critical": false,
            "elementId": 0,
            "formula": "0",
            "type": 0,
            "variance": 20
        },
        "description": "",
        "effects": [],
        "hitType": 0,
        "iconIndex": 0,
        "itypeId": 1,
        "name": "",
        "note": "",
        "occasion": 0,
        "price": 0,
        "repeats": 1,
        "scope": 7,
        "speed": 0,
        "successRate": 100,
        "tpGain": 0
    },
    {
        "id": 48,
        "animationId": 0,
        "consumable": true,
        "damage": {
            "critical": false,
            "elementId": 0,
            "formula": "0",
            "type": 0,
            "variance": 20
        },
        "description": "",
        "effects": [],
        "hitType": 0,
        "iconIndex": 0,
        "itypeId": 1,
        "name": "",
        "note": "",
        "occasion": 0,
        "price": 0,
        "repeats": 1,
        "scope": 7,
        "speed": 0,
        "successRate": 100,
        "tpGain": 0
    },
    {
        "id": 49,
        "animationId": 0,
        "consumable": true,
        "damage": {
            "critical": false,
            "elementId": 0,
            "formula": "0",
            "type": 0,
            "variance": 20
        },
        "description": "",
        "effects": [],
        "hitType": 0,
        "iconIndex": 0,
        "itypeId": 1,
        "name": "",
        "note": "",
        "occasion": 0,
        "price": 0,
        "repeats": 1,
        "scope": 7,
        "speed": 0,
        "successRate": 100,
        "tpGain": 0
    },
    {
        "id": 50,
        "animationId": 0,
        "consumable": true,
        "damage": {
            "critical": false,
            "elementId": 0,
            "formula": "0",
            "type": 0,
            "variance": 20
        },
        "description": "",
        "effects": [],
        "hitType": 0,
        "iconIndex": 0,
        "itypeId": 1,
        "name": "",
        "note": "",
        "occasion": 0,
        "price": 0,
        "repeats": 1,
        "scope": 7,
        "speed": 0,
        "successRate": 100,
        "tpGain": 0
    },
    {
        "id": 51,
        "animationId": 0,
        "consumable": false,
        "damage": {
            "critical": false,
            "elementId": 0,
            "formula": "0",
            "type": 0,
            "variance": 20
        },
        "description": "\\TA[1]A precious letter filled with a fan's feelings.\n\\V[99]\\TA[1]That's why I don't need fans who get their dicks hard and\nattack me... \\V[99]\\TA[1]\\V[99]\\TA[1]Increase in trust acquisition\nfrom clients\\TA[0]\\V[99]",
        "effects": [
            {
                "code": 44,
                "dataId": 272,
                "value1": 1,
                "value2": 0
            }
        ],
        "hitType": 0,
        "iconIndex": 0,
        "itypeId": 2,
        "name": "Fan Letter",
        "note": "<Menu Category: KeyItems>",
        "occasion": 0,
        "price": 0,
        "repeats": 1,
        "scope": 0,
        "speed": 0,
        "successRate": 100,
        "tpGain": 0
    },
    {
        "id": 52,
        "animationId": 0,
        "consumable": false,
        "damage": {
            "critical": false,
            "elementId": 0,
            "formula": "0",
            "type": 0,
            "variance": 20
        },
        "description": "\\TA[1]A cosplay costume of a cow-patterned bikini used in experiments.\n\\V[99]\\TA[1]Popular among niche customers.\n\\V[99]\\TA[1]\\V[99]\\TA[1]Increase in experience points\ngained\\TA[0]\\V[99]",
        "effects": [
            {
                "code": 44,
                "dataId": 273,
                "value1": 1,
                "value2": 0
            }
        ],
        "hitType": 0,
        "iconIndex": 1,
        "itypeId": 2,
        "name": "Cow Pattern Bikini",
        "note": "<Menu Category: KeyItems>",
        "occasion": 3,
        "price": 0,
        "repeats": 1,
        "scope": 0,
        "speed": 0,
        "successRate": 100,
        "tpGain": 0
    },
    {
        "id": 53,
        "animationId": 0,
        "consumable": false,
        "damage": {
            "critical": false,
            "elementId": 0,
            "formula": "0",
            "type": 0,
            "variance": 20
        },
        "description": "\\TA[1]The secret manual of advertising left by the <Legendary\nPromotion Pro>. \\V[99]\\TA[1]I wonder if something like this really\nworks...? \\V[99]\\TA[1]\\V[99]\\TA[1]Slight increase in magic power\ngained\\TA[0]\\V[99]",
        "effects": [
            {
                "code": 44,
                "dataId": 274,
                "value1": 1,
                "value2": 0
            }
        ],
        "hitType": 0,
        "iconIndex": 2,
        "itypeId": 2,
        "name": "Promotion Secret Technique?",
        "note": "<Menu Category: KeyItems>",
        "occasion": 3,
        "price": 0,
        "repeats": 1,
        "scope": 0,
        "speed": 0,
        "successRate": 100,
        "tpGain": 0
    },
    {
        "id": 54,
        "animationId": 0,
        "consumable": false,
        "damage": {
            "critical": false,
            "elementId": 0,
            "formula": "0",
            "type": 0,
            "variance": 20
        },
        "description": "\\TA[1]The secret manual of advertising left by the <Legendary\nPromotion Pro>. \\V[99]\\TA[1]Realization lies within oneself...\n\\V[99]\\TA[1]\\V[99]\\TA[1]A little increase in magic power\ngained\\TA[0]\\V[99]",
        "effects": [
            {
                "code": 44,
                "dataId": 275,
                "value1": 1,
                "value2": 0
            }
        ],
        "hitType": 0,
        "iconIndex": 3,
        "itypeId": 2,
        "name": "Incomplete Promotion Secret Technique",
        "note": "<Menu Category: KeyItems>",
        "occasion": 3,
        "price": 0,
        "repeats": 1,
        "scope": 0,
        "speed": 0,
        "successRate": 100,
        "tpGain": 0
    },
    {
        "id": 55,
        "animationId": 0,
        "consumable": false,
        "damage": {
            "critical": false,
            "elementId": 0,
            "formula": "0",
            "type": 0,
            "variance": 20
        },
        "description": "\\TA[1]The secret manual of advertising left by the <Legendary\nPromotion Pro>. \\V[99]\\TA[1]Teachings are nothing more than an array\nof characters, \\V[99]\\TA[1]Only those who believe in themselves will\nmove forward. \\V[99]\\TA[1]Increase in magic power gained\\TA[0]\\V[99]",
        "effects": [
            {
                "code": 44,
                "dataId": 276,
                "value1": 1,
                "value2": 0
            }
        ],
        "hitType": 0,
        "iconIndex": 4,
        "itypeId": 2,
        "name": "Promotion Secret Technique",
        "note": "<Menu Category: KeyItems>",
        "occasion": 3,
        "price": 0,
        "repeats": 1,
        "scope": 0,
        "speed": 0,
        "successRate": 100,
        "tpGain": 0
    },
    {
        "id": 56,
        "animationId": 0,
        "consumable": false,
        "damage": {
            "critical": false,
            "elementId": 0,
            "formula": "0",
            "type": 0,
            "variance": 20
        },
        "description": "\\TA[1]A token of friendship from the macho demon tribe.\n\\V[99]\\TA[1]Not even death can separate the two, hence,\n\\V[99]\\TA[1]It's like... \\V[99]\\TA[1]Reduction of 1 fatigue in\nschedule\\TA[0]\\V[99]",
        "effects": [
            {
                "code": 44,
                "dataId": 277,
                "value1": 1,
                "value2": 0
            }
        ],
        "hitType": 0,
        "iconIndex": 5,
        "itypeId": 2,
        "name": "Proof of Friendship",
        "note": "<Menu Category: KeyItems>",
        "occasion": 3,
        "price": 0,
        "repeats": 1,
        "scope": 0,
        "speed": 0,
        "successRate": 100,
        "tpGain": 0
    },
    {
        "id": 57,
        "animationId": 0,
        "consumable": false,
        "damage": {
            "critical": false,
            "elementId": 0,
            "formula": "0",
            "type": 0,
            "variance": 20
        },
        "description": "\\TA[1]An experimental report about a friend from the macho demon\ntribe. \\V[99]\\TA[1]It contains tremendous details... \\TA[0]\\V[99]",
        "effects": [
            {
                "code": 44,
                "dataId": 278,
                "value1": 1,
                "value2": 0
            }
        ],
        "hitType": 0,
        "iconIndex": 6,
        "itypeId": 2,
        "name": "Experiment Report",
        "note": "<Menu Category: KeyItems>",
        "occasion": 3,
        "price": 0,
        "repeats": 1,
        "scope": 0,
        "speed": 0,
        "successRate": 100,
        "tpGain": 0
    },
    {
        "id": 58,
        "animationId": 0,
        "consumable": true,
        "damage": {
            "critical": false,
            "elementId": 0,
            "formula": "0",
            "type": 0,
            "variance": 20
        },
        "description": "",
        "effects": [],
        "hitType": 0,
        "iconIndex": 0,
        "itypeId": 1,
        "name": "",
        "note": "",
        "occasion": 0,
        "price": 0,
        "repeats": 1,
        "scope": 7,
        "speed": 0,
        "successRate": 100,
        "tpGain": 0
    },
    {
        "id": 59,
        "animationId": 0,
        "consumable": true,
        "damage": {
            "critical": false,
            "elementId": 0,
            "formula": "0",
            "type": 0,
            "variance": 20
        },
        "description": "",
        "effects": [],
        "hitType": 0,
        "iconIndex": 0,
        "itypeId": 1,
        "name": "",
        "note": "",
        "occasion": 0,
        "price": 0,
        "repeats": 1,
        "scope": 7,
        "speed": 0,
        "successRate": 100,
        "tpGain": 0
    },
    {
        "id": 60,
        "animationId": 0,
        "consumable": true,
        "damage": {
            "critical": false,
            "elementId": 0,
            "formula": "0",
            "type": 0,
            "variance": 20
        },
        "description": "",
        "effects": [],
        "hitType": 0,
        "iconIndex": 0,
        "itypeId": 1,
        "name": "",
        "note": "",
        "occasion": 0,
        "price": 0,
        "repeats": 1,
        "scope": 7,
        "speed": 0,
        "successRate": 100,
        "tpGain": 0
    },
    {
        "id": 61,
        "animationId": 0,
        "consumable": true,
        "damage": {
            "critical": false,
            "elementId": 0,
            "formula": "0",
            "type": 0,
            "variance": 20
        },
        "description": "",
        "effects": [],
        "hitType": 0,
        "iconIndex": 0,
        "itypeId": 2,
        "name": "WP01",
        "note": "",
        "occasion": 3,
        "price": 0,
        "repeats": 1,
        "scope": 7,
        "speed": 0,
        "successRate": 100,
        "tpGain": 0
    },
    {
        "id": 62,
        "animationId": 0,
        "consumable": true,
        "damage": {
            "critical": false,
            "elementId": 0,
            "formula": "0",
            "type": 0,
            "variance": 20
        },
        "description": "",
        "effects": [],
        "hitType": 0,
        "iconIndex": 0,
        "itypeId": 2,
        "name": "WP02",
        "note": "",
        "occasion": 3,
        "price": 0,
        "repeats": 1,
        "scope": 7,
        "speed": 0,
        "successRate": 100,
        "tpGain": 0
    },
    {
        "id": 63,
        "animationId": 0,
        "consumable": true,
        "damage": {
            "critical": false,
            "elementId": 0,
            "formula": "0",
            "type": 0,
            "variance": 20
        },
        "description": "",
        "effects": [],
        "hitType": 0,
        "iconIndex": 0,
        "itypeId": 2,
        "name": "WP03",
        "note": "",
        "occasion": 3,
        "price": 0,
        "repeats": 1,
        "scope": 7,
        "speed": 0,
        "successRate": 100,
        "tpGain": 0
    },
    {
        "id": 64,
        "animationId": 0,
        "consumable": true,
        "damage": {
            "critical": false,
            "elementId": 0,
            "formula": "0",
            "type": 0,
            "variance": 20
        },
        "description": "",
        "effects": [],
        "hitType": 0,
        "iconIndex": 0,
        "itypeId": 2,
        "name": "WP04",
        "note": "",
        "occasion": 3,
        "price": 0,
        "repeats": 1,
        "scope": 7,
        "speed": 0,
        "successRate": 100,
        "tpGain": 0
    },
    {
        "id": 65,
        "animationId": 0,
        "consumable": true,
        "damage": {
            "critical": false,
            "elementId": 0,
            "formula": "0",
            "type": 0,
            "variance": 20
        },
        "description": "",
        "effects": [],
        "hitType": 0,
        "iconIndex": 0,
        "itypeId": 2,
        "name": "WP05",
        "note": "",
        "occasion": 3,
        "price": 0,
        "repeats": 1,
        "scope": 7,
        "speed": 0,
        "successRate": 100,
        "tpGain": 0
    },
    {
        "id": 66,
        "animationId": 0,
        "consumable": true,
        "damage": {
            "critical": false,
            "elementId": 0,
            "formula": "0",
            "type": 0,
            "variance": 20
        },
        "description": "",
        "effects": [],
        "hitType": 0,
        "iconIndex": 0,
        "itypeId": 2,
        "name": "WP06",
        "note": "",
        "occasion": 3,
        "price": 0,
        "repeats": 1,
        "scope": 7,
        "speed": 0,
        "successRate": 100,
        "tpGain": 0
    },
    {
        "id": 67,
        "animationId": 0,
        "consumable": true,
        "damage": {
            "critical": false,
            "elementId": 0,
            "formula": "0",
            "type": 0,
            "variance": 20
        },
        "description": "",
        "effects": [],
        "hitType": 0,
        "iconIndex": 0,
        "itypeId": 1,
        "name": "",
        "note": "",
        "occasion": 0,
        "price": 0,
        "repeats": 1,
        "scope": 7,
        "speed": 0,
        "successRate": 100,
        "tpGain": 0
    },
    {
        "id": 68,
        "animationId": 0,
        "consumable": true,
        "damage": {
            "critical": false,
            "elementId": 0,
            "formula": "0",
            "type": 0,
            "variance": 20
        },
        "description": "",
        "effects": [],
        "hitType": 0,
        "iconIndex": 0,
        "itypeId": 1,
        "name": "",
        "note": "",
        "occasion": 0,
        "price": 0,
        "repeats": 1,
        "scope": 7,
        "speed": 0,
        "successRate": 100,
        "tpGain": 0
    },
    {
        "id": 69,
        "animationId": 0,
        "consumable": true,
        "damage": {
            "critical": false,
            "elementId": 0,
            "formula": "0",
            "type": 0,
            "variance": 20
        },
        "description": "",
        "effects": [],
        "hitType": 0,
        "iconIndex": 0,
        "itypeId": 1,
        "name": "",
        "note": "",
        "occasion": 0,
        "price": 0,
        "repeats": 1,
        "scope": 7,
        "speed": 0,
        "successRate": 100,
        "tpGain": 0
    },
    {
        "id": 70,
        "animationId": 0,
        "consumable": true,
        "damage": {
            "critical": false,
            "elementId": 0,
            "formula": "0",
            "type": 0,
            "variance": 20
        },
        "description": "",
        "effects": [],
        "hitType": 0,
        "iconIndex": 0,
        "itypeId": 1,
        "name": "",
        "note": "",
        "occasion": 0,
        "price": 0,
        "repeats": 1,
        "scope": 7,
        "speed": 0,
        "successRate": 100,
        "tpGain": 0
    },
    {
        "id": 71,
        "animationId": 0,
        "consumable": false,
        "damage": {
            "critical": false,
            "elementId": 0,
            "formula": "0",
            "type": 0,
            "variance": 20
        },
        "description": "The article details the series of disappearances involving succubi.\nThere are no commonalities among the victims, and five have vanished\nover the course of two months. Whether it's a planned crime or a mere\ncoincidence remains a question as the incident gradually fades into\nobscurity...",
        "effects": [
            {
                "code": 44,
                "dataId": 280,
                "value1": 1,
                "value2": 0
            }
        ],
        "hitType": 0,
        "iconIndex": 16,
        "itypeId": 2,
        "name": "Article on the Mysterious Series of Disappearances",
        "note": "<Menu Category: KeyItems>",
        "occasion": 0,
        "price": 0,
        "repeats": 1,
        "scope": 0,
        "speed": 0,
        "successRate": 100,
        "tpGain": 0
    },
    {
        "id": 72,
        "animationId": 0,
        "consumable": false,
        "damage": {
            "critical": false,
            "elementId": 0,
            "formula": "0",
            "type": 0,
            "variance": 20
        },
        "description": "This media guideline serves as the foundation to grant high value to\nthe succubus industry as a new renewable energy source and to garner\nfull support from the general populace as a future national industry.\nThe published guidelines do not appear to be intentionally damaged...",
        "effects": [
            {
                "code": 44,
                "dataId": 281,
                "value1": 1,
                "value2": 0
            }
        ],
        "hitType": 0,
        "iconIndex": 17,
        "itypeId": 2,
        "name": "Succubus First Industry Media Guidelines",
        "note": "<Menu Category: KeyItems>",
        "occasion": 0,
        "price": 0,
        "repeats": 1,
        "scope": 0,
        "speed": 0,
        "successRate": 100,
        "tpGain": 0
    },
    {
        "id": 73,
        "animationId": 0,
        "consumable": false,
        "damage": {
            "critical": false,
            "elementId": 0,
            "formula": "0",
            "type": 0,
            "variance": 20
        },
        "description": "These are fragments of documents that were found shredded in the trash\ncan, marked with a distinctive pattern.",
        "effects": [
            {
                "code": 44,
                "dataId": 282,
                "value1": 1,
                "value2": 0
            }
        ],
        "hitType": 0,
        "iconIndex": 18,
        "itypeId": 2,
        "name": "Torn Documents",
        "note": "<Menu Category: KeyItems>",
        "occasion": 0,
        "price": 0,
        "repeats": 1,
        "scope": 0,
        "speed": 0,
        "successRate": 100,
        "tpGain": 0
    },
    {
        "id": 74,
        "animationId": 0,
        "consumable": false,
        "damage": {
            "critical": false,
            "elementId": 0,
            "formula": "0",
            "type": 0,
            "variance": 20
        },
        "description": "A draft article about the death of a client who used the services of\nthe succubus industry. It coincides with the issuance of the media\nguidelines and seems to have been rejected for publication. Despite\nthe date being quite old, it was found tucked away in a drawer corner.\nIt is written that the client died from having their life force\ndrained excessively during sexual intercourse.",
        "effects": [
            {
                "code": 44,
                "dataId": 283,
                "value1": 1,
                "value2": 0
            }
        ],
        "hitType": 0,
        "iconIndex": 19,
        "itypeId": 2,
        "name": "Article on the Death of a Client Using Succubus First Industry Services",
        "note": "<Menu Category: KeyItems>",
        "occasion": 0,
        "price": 0,
        "repeats": 1,
        "scope": 0,
        "speed": 0,
        "successRate": 100,
        "tpGain": 0
    },
    {
        "id": 75,
        "animationId": 0,
        "consumable": false,
        "damage": {
            "critical": false,
            "elementId": 0,
            "formula": "0",
            "type": 0,
            "variance": 20
        },
        "description": "A document entrusted by an employee of a logistics company for\ntransmission. It seems that it should not be opened...",
        "effects": [
            {
                "code": 44,
                "dataId": 285,
                "value1": 1,
                "value2": 0
            }
        ],
        "hitType": 0,
        "iconIndex": 32,
        "itypeId": 2,
        "name": "Requested Documents",
        "note": "<Menu Category: KeyItems>",
        "occasion": 3,
        "price": 0,
        "repeats": 1,
        "scope": 0,
        "speed": 0,
        "successRate": 100,
        "tpGain": 0
    },
    {
        "id": 76,
        "animationId": 0,
        "consumable": false,
        "damage": {
            "critical": false,
            "elementId": 0,
            "formula": "0",
            "type": 0,
            "variance": 20
        },
        "description": "An apparatus instructed to be worn by employees at a research\ninstitution. It's so customized to one's body that it gives\ngoosebumps...",
        "effects": [
            {
                "code": 44,
                "dataId": 286,
                "value1": 1,
                "value2": 0
            }
        ],
        "hitType": 0,
        "iconIndex": 33,
        "itypeId": 2,
        "name": "Suspicious Device",
        "note": "<Menu Category: KeyItems>",
        "occasion": 3,
        "price": 0,
        "repeats": 1,
        "scope": 0,
        "speed": 0,
        "successRate": 100,
        "tpGain": 0
    },
    {
        "id": 77,
        "animationId": 0,
        "consumable": false,
        "damage": {
            "critical": false,
            "elementId": 0,
            "formula": "0",
            "type": 0,
            "variance": 20
        },
        "description": "A report found at a research institution. It suggests that the more\nsuccubi become dependent on vital energy, the more they also become\ndependent on men. This is thought to be because succubi have\nhistorically been used as consumables.",
        "effects": [
            {
                "code": 44,
                "dataId": 287,
                "value1": 1,
                "value2": 0
            }
        ],
        "hitType": 0,
        "iconIndex": 34,
        "itypeId": 2,
        "name": "Succubus Essence Dependency Analysis Report",
        "note": "<Menu Category: KeyItems>",
        "occasion": 0,
        "price": 0,
        "repeats": 1,
        "scope": 0,
        "speed": 0,
        "successRate": 100,
        "tpGain": 0
    },
    {
        "id": 78,
        "animationId": 0,
        "consumable": false,
        "damage": {
            "critical": false,
            "elementId": 0,
            "formula": "0",
            "type": 0,
            "variance": 20
        },
        "description": "A mysterious disk found in a computer exchanged at a research\ninstitution. A player is needed. There is nothing written on its\nsurface.",
        "effects": [
            {
                "code": 44,
                "dataId": 288,
                "value1": 1,
                "value2": 0
            }
        ],
        "hitType": 0,
        "iconIndex": 35,
        "itypeId": 2,
        "name": "Disk",
        "note": "<Menu Category: KeyItems>",
        "occasion": 3,
        "price": 0,
        "repeats": 1,
        "scope": 0,
        "speed": 0,
        "successRate": 100,
        "tpGain": 0
    },
    {
        "id": 79,
        "animationId": 0,
        "consumable": false,
        "damage": {
            "critical": false,
            "elementId": 0,
            "formula": "0",
            "type": 0,
            "variance": 20
        },
        "description": "Accusation materials for an insolent new employee. It documents the\nunfair treatment they received at the succubus industry.",
        "effects": [
            {
                "code": 44,
                "dataId": 289,
                "value1": 1,
                "value2": 0
            }
        ],
        "hitType": 0,
        "iconIndex": 36,
        "itypeId": 2,
        "name": "Accusation Materials",
        "note": "<Menu Category: KeyItems>",
        "occasion": 0,
        "price": 0,
        "repeats": 1,
        "scope": 0,
        "speed": 0,
        "successRate": 100,
        "tpGain": 0
    },
    {
        "id": 80,
        "animationId": 0,
        "consumable": false,
        "damage": {
            "critical": false,
            "elementId": 0,
            "formula": "0",
            "type": 0,
            "variance": 20
        },
        "description": "???",
        "effects": [
            {
                "code": 44,
                "dataId": 290,
                "value1": 1,
                "value2": 0
            }
        ],
        "hitType": 0,
        "iconIndex": 37,
        "itypeId": 2,
        "name": "Mysterious Virus Culture Fluid",
        "note": "<Menu Category: KeyItems>",
        "occasion": 3,
        "price": 0,
        "repeats": 1,
        "scope": 0,
        "speed": 0,
        "successRate": 100,
        "tpGain": 0
    },
    {
        "id": 81,
        "animationId": 0,
        "consumable": false,
        "damage": {
            "critical": false,
            "elementId": 0,
            "formula": "0",
            "type": 0,
            "variance": 20
        },
        "description": "A box found at a research institution containing a virus... its\ncontents are...",
        "effects": [
            {
                "code": 44,
                "dataId": 291,
                "value1": 1,
                "value2": 0
            }
        ],
        "hitType": 0,
        "iconIndex": 38,
        "itypeId": 2,
        "name": "Box Containing Virus Solution",
        "note": "<Menu Category: KeyItems>",
        "occasion": 3,
        "price": 0,
        "repeats": 1,
        "scope": 0,
        "speed": 0,
        "successRate": 100,
        "tpGain": 0
    },
    {
        "id": 82,
        "animationId": 0,
        "consumable": false,
        "damage": {
            "critical": false,
            "elementId": 0,
            "formula": "0",
            "type": 0,
            "variance": 20
        },
        "description": "A box with a biological hazard warning label attached. What is written\ncannot be read...",
        "effects": [
            {
                "code": 44,
                "dataId": 293,
                "value1": 1,
                "value2": 0
            }
        ],
        "hitType": 0,
        "iconIndex": 48,
        "itypeId": 2,
        "name": "Mysterious Box",
        "note": "<Menu Category: KeyItems>",
        "occasion": 3,
        "price": 0,
        "repeats": 1,
        "scope": 0,
        "speed": 0,
        "successRate": 100,
        "tpGain": 0
    },
    {
        "id": 83,
        "animationId": 0,
        "consumable": false,
        "damage": {
            "critical": false,
            "elementId": 0,
            "formula": "0",
            "type": 0,
            "variance": 20
        },
        "description": "A key with a unique pattern engraved on it. It has a pattern similar\nto that on the <torn document>.",
        "effects": [
            {
                "code": 44,
                "dataId": 294,
                "value1": 1,
                "value2": 0
            }
        ],
        "hitType": 0,
        "iconIndex": 49,
        "itypeId": 2,
        "name": "Key with a Pattern Drawn on It",
        "note": "<Menu Category: KeyItems>",
        "occasion": 3,
        "price": 0,
        "repeats": 1,
        "scope": 0,
        "speed": 0,
        "successRate": 100,
        "tpGain": 0
    },
    {
        "id": 84,
        "animationId": 0,
        "consumable": false,
        "damage": {
            "critical": false,
            "elementId": 0,
            "formula": "0",
            "type": 0,
            "variance": 20
        },
        "description": "A card key found at a logistics company. Its purpose is unknown.",
        "effects": [
            {
                "code": 44,
                "dataId": 295,
                "value1": 1,
                "value2": 0
            }
        ],
        "hitType": 0,
        "iconIndex": 50,
        "itypeId": 2,
        "name": "Card Key",
        "note": "<Menu Category: KeyItems>",
        "occasion": 3,
        "price": 0,
        "repeats": 1,
        "scope": 0,
        "speed": 0,
        "successRate": 100,
        "tpGain": 0
    },
    {
        "id": 85,
        "animationId": 0,
        "consumable": false,
        "damage": {
            "critical": false,
            "elementId": 0,
            "formula": "0",
            "type": 0,
            "variance": 20
        },
        "description": "A map detailing the city's water supply facilities. What could this be\nused for...?",
        "effects": [
            {
                "code": 44,
                "dataId": 296,
                "value1": 1,
                "value2": 0
            }
        ],
        "hitType": 0,
        "iconIndex": 51,
        "itypeId": 2,
        "name": "Map of the Water Supply Facility",
        "note": "<Menu Category: KeyItems>",
        "occasion": 0,
        "price": 0,
        "repeats": 1,
        "scope": 0,
        "speed": 0,
        "successRate": 100,
        "tpGain": 0
    },
    {
        "id": 86,
        "animationId": 0,
        "consumable": false,
        "damage": {
            "critical": false,
            "elementId": 0,
            "formula": "0",
            "type": 0,
            "variance": 20
        },
        "description": "Documents containing all information regarding the city's water supply\nfacilities' equipment. What could this be used for...?",
        "effects": [
            {
                "code": 44,
                "dataId": 297,
                "value1": 1,
                "value2": 0
            }
        ],
        "hitType": 0,
        "iconIndex": 52,
        "itypeId": 2,
        "name": "Water Supply Facility Equipment Documents",
        "note": "<Menu Category: KeyItems>",
        "occasion": 0,
        "price": 0,
        "repeats": 1,
        "scope": 0,
        "speed": 0,
        "successRate": 100,
        "tpGain": 0
    },
    {
        "id": 87,
        "animationId": 0,
        "consumable": false,
        "damage": {
            "critical": false,
            "elementId": 0,
            "formula": "0",
            "type": 0,
            "variance": 20
        },
        "description": "A business card of a demon race that seems familiar. There is a\ndistinctive scar on the face...",
        "effects": [
            {
                "code": 44,
                "dataId": 299,
                "value1": 1,
                "value2": 0
            }
        ],
        "hitType": 0,
        "iconIndex": 64,
        "itypeId": 2,
        "name": "Familiar Demon's Business Card",
        "note": "<Menu Category: KeyItems>",
        "occasion": 0,
        "price": 0,
        "repeats": 1,
        "scope": 0,
        "speed": 0,
        "successRate": 100,
        "tpGain": 0
    },
    {
        "id": 88,
        "animationId": 0,
        "consumable": false,
        "damage": {
            "critical": false,
            "elementId": 0,
            "formula": "0",
            "type": 0,
            "variance": 20
        },
        "description": "Documents containing information about a demon race that seems\nfamiliar. The details are unclear, but it appears to list their past\ndeeds and experiences.",
        "effects": [
            {
                "code": 44,
                "dataId": 300,
                "value1": 1,
                "value2": 0
            }
        ],
        "hitType": 0,
        "iconIndex": 65,
        "itypeId": 2,
        "name": "Familiar Demon's Documents",
        "note": "<Menu Category: KeyItems>",
        "occasion": 0,
        "price": 0,
        "repeats": 1,
        "scope": 0,
        "speed": 0,
        "successRate": 100,
        "tpGain": 0
    },
    {
        "id": 89,
        "animationId": 0,
        "consumable": false,
        "damage": {
            "critical": false,
            "elementId": 0,
            "formula": "0",
            "type": 0,
            "variance": 20
        },
        "description": "Mysterious documents. They contain coordinates to a specific location\nand list of preparation items with unclear serial numbers.",
        "effects": [
            {
                "code": 44,
                "dataId": 301,
                "value1": 1,
                "value2": 0
            }
        ],
        "hitType": 0,
        "iconIndex": 66,
        "itypeId": 2,
        "name": "Mysterious Documents",
        "note": "<Menu Category: KeyItems>",
        "occasion": 0,
        "price": 0,
        "repeats": 1,
        "scope": 0,
        "speed": 0,
        "successRate": 100,
        "tpGain": 0
    },
    {
        "id": 90,
        "animationId": 0,
        "consumable": false,
        "damage": {
            "critical": false,
            "elementId": 0,
            "formula": "0",
            "type": 0,
            "variance": 20
        },
        "description": "Documents about specific coordinates and preparation items required.\nThey list serial numbers for handcuffs and rope found in a cabinet.",
        "effects": [
            {
                "code": 44,
                "dataId": 302,
                "value1": 1,
                "value2": 0
            }
        ],
        "hitType": 0,
        "iconIndex": 66,
        "itypeId": 2,
        "name": "Work Instruction Documents",
        "note": "<Menu Category: KeyItems>",
        "occasion": 0,
        "price": 0,
        "repeats": 1,
        "scope": 0,
        "speed": 0,
        "successRate": 100,
        "tpGain": 0
    },
    {
        "id": 91,
        "animationId": 0,
        "consumable": false,
        "damage": {
            "critical": false,
            "elementId": 0,
            "formula": "0",
            "type": 0,
            "variance": 20
        },
        "description": "Handcuffs found in a security company's cabinet. They are marked with\nP337187.",
        "effects": [
            {
                "code": 44,
                "dataId": 303,
                "value1": 1,
                "value2": 0
            }
        ],
        "hitType": 0,
        "iconIndex": 67,
        "itypeId": 2,
        "name": "Handcuffs",
        "note": "<Menu Category: KeyItems>",
        "occasion": 3,
        "price": 0,
        "repeats": 1,
        "scope": 0,
        "speed": 0,
        "successRate": 100,
        "tpGain": 0
    },
    {
        "id": 92,
        "animationId": 0,
        "consumable": false,
        "damage": {
            "critical": false,
            "elementId": 0,
            "formula": "0",
            "type": 0,
            "variance": 20
        },
        "description": "A rope found in a security company's cabinet. It is marked with\nP409420.",
        "effects": [
            {
                "code": 44,
                "dataId": 304,
                "value1": 1,
                "value2": 0
            }
        ],
        "hitType": 0,
        "iconIndex": 68,
        "itypeId": 2,
        "name": "Rope",
        "note": "<Menu Category: KeyItems>",
        "occasion": 3,
        "price": 0,
        "repeats": 1,
        "scope": 0,
        "speed": 0,
        "successRate": 100,
        "tpGain": 0
    },
    {
        "id": 93,
        "animationId": 0,
        "consumable": false,
        "damage": {
            "critical": false,
            "elementId": 0,
            "formula": "0",
            "type": 0,
            "variance": 20
        },
        "description": "Detailed information about the security system of the city's water\nsupply facilities is documented here. What could this be used for...?",
        "effects": [
            {
                "code": 44,
                "dataId": 305,
                "value1": 1,
                "value2": 0
            }
        ],
        "hitType": 0,
        "iconIndex": 69,
        "itypeId": 2,
        "name": "Security System of the Water Supply Facility",
        "note": "<Menu Category: KeyItems>",
        "occasion": 0,
        "price": 0,
        "repeats": 1,
        "scope": 0,
        "speed": 0,
        "successRate": 100,
        "tpGain": 0
    },
    {
        "id": 94,
        "animationId": 0,
        "consumable": false,
        "damage": {
            "critical": false,
            "elementId": 0,
            "formula": "0",
            "type": 0,
            "variance": 20
        },
        "description": "An apparatus instructed to be worn by employees at a research\ninstitution. Data collection has been completed.",
        "effects": [
            {
                "code": 44,
                "dataId": 286,
                "value1": 1,
                "value2": 0
            }
        ],
        "hitType": 0,
        "iconIndex": 33,
        "itypeId": 2,
        "name": "Suspicious Device (Completed)",
        "note": "<Menu Category: KeyItems>",
        "occasion": 3,
        "price": 0,
        "repeats": 1,
        "scope": 0,
        "speed": 0,
        "successRate": 100,
        "tpGain": 0
    },
    {
        "id": 95,
        "animationId": 0,
        "consumable": true,
        "damage": {
            "critical": false,
            "elementId": 0,
            "formula": "0",
            "type": 0,
            "variance": 20
        },
        "description": "",
        "effects": [],
        "hitType": 0,
        "iconIndex": 0,
        "itypeId": 1,
        "name": "",
        "note": "",
        "occasion": 0,
        "price": 0,
        "repeats": 1,
        "scope": 7,
        "speed": 0,
        "successRate": 100,
        "tpGain": 0
    },
    {
        "id": 96,
        "animationId": 0,
        "consumable": true,
        "damage": {
            "critical": false,
            "elementId": 0,
            "formula": "0",
            "type": 0,
            "variance": 20
        },
        "description": "Using this will increase magical power by 5000.",
        "effects": [
            {
                "code": 44,
                "dataId": 267,
                "value1": 1,
                "value2": 0
            }
        ],
        "hitType": 0,
        "iconIndex": 80,
        "itypeId": 2,
        "name": "Magic Power Capsule (Small)",
        "note": "<Menu Category: KeyItems>",
        "occasion": 0,
        "price": 0,
        "repeats": 1,
        "scope": 0,
        "speed": 0,
        "successRate": 100,
        "tpGain": 0
    },
    {
        "id": 97,
        "animationId": 0,
        "consumable": true,
        "damage": {
            "critical": false,
            "elementId": 0,
            "formula": "0",
            "type": 0,
            "variance": 20
        },
        "description": "Using this will increase magical power by 20000.",
        "effects": [
            {
                "code": 44,
                "dataId": 268,
                "value1": 1,
                "value2": 0
            }
        ],
        "hitType": 0,
        "iconIndex": 81,
        "itypeId": 2,
        "name": "Magic Power Capsule (Medium)",
        "note": "<Menu Category: KeyItems>",
        "occasion": 0,
        "price": 0,
        "repeats": 1,
        "scope": 0,
        "speed": 0,
        "successRate": 100,
        "tpGain": 0
    },
    {
        "id": 98,
        "animationId": 0,
        "consumable": true,
        "damage": {
            "critical": false,
            "elementId": 0,
            "formula": "0",
            "type": 0,
            "variance": 20
        },
        "description": "Using this will increase magical power by 50000.",
        "effects": [
            {
                "code": 44,
                "dataId": 269,
                "value1": 1,
                "value2": 0
            }
        ],
        "hitType": 0,
        "iconIndex": 82,
        "itypeId": 2,
        "name": "Magic Power Capsule (Large)",
        "note": "<Menu Category: KeyItems>",
        "occasion": 0,
        "price": 0,
        "repeats": 1,
        "scope": 0,
        "speed": 0,
        "successRate": 100,
        "tpGain": 0
    },
    {
        "id": 99,
        "animationId": 0,
        "consumable": true,
        "damage": {
            "critical": false,
            "elementId": 0,
            "formula": "0",
            "type": 0,
            "variance": 20
        },
        "description": "A protein imbued with the wishes of an exercise-loving demon race\nmember. They are willing to sacrifice everything to reach their\ndesired place. It recovers fatigue by 10 points.",
        "effects": [
            {
                "code": 44,
                "dataId": 265,
                "value1": 1,
                "value2": 0
            }
        ],
        "hitType": 0,
        "iconIndex": 83,
        "itypeId": 2,
        "name": "Modified Protein",
        "note": "",
        "occasion": 0,
        "price": 0,
        "repeats": 1,
        "scope": 0,
        "speed": 0,
        "successRate": 100,
        "tpGain": 0
    },
    {
        "id": 100,
        "animationId": 0,
        "consumable": true,
        "damage": {
            "critical": false,
            "elementId": 0,
            "formula": "0",
            "type": 0,
            "variance": 20
        },
        "description": "A medicine that fully restores physical strength and stamina... or\ndoes not. No one can guarantee the side effects. It recovers fatigue\nby 40 points.",
        "effects": [
            {
                "code": 44,
                "dataId": 266,
                "value1": 1,
                "value2": 0
            }
        ],
        "hitType": 0,
        "iconIndex": 84,
        "itypeId": 2,
        "name": "Modern Elixir",
        "note": "",
        "occasion": 0,
        "price": 0,
        "repeats": 1,
        "scope": 0,
        "speed": 0,
        "successRate": 100,
        "tpGain": 0
    },
    {
        "id": 101,
        "animationId": 0,
        "consumable": true,
        "damage": {
            "critical": false,
            "elementId": 0,
            "formula": "0",
            "type": 0,
            "variance": 20
        },
        "description": "A friend who is an office worker. It recovers fatigue by 10 points.",
        "effects": [
            {
                "code": 44,
                "dataId": 265,
                "value1": 1,
                "value2": 0
            }
        ],
        "hitType": 0,
        "iconIndex": 85,
        "itypeId": 2,
        "name": "Canned Coffee",
        "note": "<Menu Category: KeyItems>",
        "occasion": 0,
        "price": 0,
        "repeats": 1,
        "scope": 0,
        "speed": 0,
        "successRate": 100,
        "tpGain": 0
    },
    {
        "id": 102,
        "animationId": 0,
        "consumable": true,
        "damage": {
            "critical": false,
            "elementId": 0,
            "formula": "0",
            "type": 0,
            "variance": 20
        },
        "description": "Caffeine for those with unusual tastes. It recovers fatigue by 20\npoints.",
        "effects": [
            {
                "code": 44,
                "dataId": 264,
                "value1": 1,
                "value2": 0
            }
        ],
        "hitType": 0,
        "iconIndex": 86,
        "itypeId": 2,
        "name": "Canned Green Tea",
        "note": "<Menu Category: KeyItems>",
        "occasion": 0,
        "price": 0,
        "repeats": 1,
        "scope": 0,
        "speed": 0,
        "successRate": 100,
        "tpGain": 0
    },
    {
        "id": 103,
        "animationId": 0,
        "consumable": true,
        "damage": {
            "critical": false,
            "elementId": 0,
            "formula": "0",
            "type": 0,
            "variance": 20
        },
        "description": "",
        "effects": [],
        "hitType": 0,
        "iconIndex": 0,
        "itypeId": 1,
        "name": "",
        "note": "",
        "occasion": 0,
        "price": 0,
        "repeats": 1,
        "scope": 7,
        "speed": 0,
        "successRate": 100,
        "tpGain": 0
    },
    {
        "id": 104,
        "animationId": 0,
        "consumable": true,
        "damage": {
            "critical": false,
            "elementId": 0,
            "formula": "0",
            "type": 0,
            "variance": 20
        },
        "description": "",
        "effects": [],
        "hitType": 0,
        "iconIndex": 0,
        "itypeId": 1,
        "name": "",
        "note": "",
        "occasion": 0,
        "price": 0,
        "repeats": 1,
        "scope": 7,
        "speed": 0,
        "successRate": 100,
        "tpGain": 0
    },
    {
        "id": 105,
        "animationId": 0,
        "consumable": true,
        "damage": {
            "critical": false,
            "elementId": 0,
            "formula": "0",
            "type": 0,
            "variance": 20
        },
        "description": "",
        "effects": [],
        "hitType": 0,
        "iconIndex": 0,
        "itypeId": 1,
        "name": "",
        "note": "",
        "occasion": 0,
        "price": 0,
        "repeats": 1,
        "scope": 7,
        "speed": 0,
        "successRate": 100,
        "tpGain": 0
    },
    {
        "id": 106,
        "animationId": 0,
        "consumable": true,
        "damage": {
            "critical": false,
            "elementId": 0,
            "formula": "0",
            "type": 0,
            "variance": 20
        },
        "description": "",
        "effects": [],
        "hitType": 0,
        "iconIndex": 0,
        "itypeId": 1,
        "name": "",
        "note": "",
        "occasion": 0,
        "price": 0,
        "repeats": 1,
        "scope": 7,
        "speed": 0,
        "successRate": 100,
        "tpGain": 0
    },
    {
        "id": 107,
        "animationId": 0,
        "consumable": true,
        "damage": {
            "critical": false,
            "elementId": 0,
            "formula": "0",
            "type": 0,
            "variance": 20
        },
        "description": "",
        "effects": [],
        "hitType": 0,
        "iconIndex": 0,
        "itypeId": 1,
        "name": "",
        "note": "",
        "occasion": 0,
        "price": 0,
        "repeats": 1,
        "scope": 7,
        "speed": 0,
        "successRate": 100,
        "tpGain": 0
    },
    {
        "id": 108,
        "animationId": 0,
        "consumable": true,
        "damage": {
            "critical": false,
            "elementId": 0,
            "formula": "0",
            "type": 0,
            "variance": 20
        },
        "description": "",
        "effects": [],
        "hitType": 0,
        "iconIndex": 0,
        "itypeId": 1,
        "name": "",
        "note": "",
        "occasion": 0,
        "price": 0,
        "repeats": 1,
        "scope": 7,
        "speed": 0,
        "successRate": 100,
        "tpGain": 0
    },
    {
        "id": 109,
        "animationId": 0,
        "consumable": true,
        "damage": {
            "critical": false,
            "elementId": 0,
            "formula": "0",
            "type": 0,
            "variance": 20
        },
        "description": "",
        "effects": [],
        "hitType": 0,
        "iconIndex": 0,
        "itypeId": 1,
        "name": "",
        "note": "",
        "occasion": 0,
        "price": 0,
        "repeats": 1,
        "scope": 7,
        "speed": 0,
        "successRate": 100,
        "tpGain": 0
    },
    {
        "id": 110,
        "animationId": 0,
        "consumable": true,
        "damage": {
            "critical": false,
            "elementId": 0,
            "formula": "0",
            "type": 0,
            "variance": 20
        },
        "description": "",
        "effects": [],
        "hitType": 0,
        "iconIndex": 0,
        "itypeId": 1,
        "name": "",
        "note": "",
        "occasion": 0,
        "price": 0,
        "repeats": 1,
        "scope": 7,
        "speed": 0,
        "successRate": 100,
        "tpGain": 0
    }
]